toolgrad/__init__.py
toolgrad/states.py
toolgrad/data/toolbench/filtered_v1.json
toolgrad/data/toolbench/filtered_v1.jsonl
toolgrad/data/toolbench/hash_to_tool_prefix.json
toolgrad/data/toolbench/tool_to_hash_prefix.json
toolgrad/modules/__init__.py
toolgrad/modules/graph_lib.py
toolgrad/modules/module_lib.py
toolgrad/modules/prompt_lib.py
toolgrad/prebuilt/__init__.py
toolgrad/prebuilt/toolgrad_on_mcp.py
toolgrad/prebuilt/toolgrad_on_toolbench.py
toolgrad/utils/__init__.py
toolgrad/utils/data.py
toolgrad/utils/drive.py
toolgrad/utils/langchain.py
toolgrad/utils/load_example.py
toolgrad/utils/log_utils.py
toolgrad/utils/mcp.py
toolgrad/utils/toolbench/templates.py
toolgrad/utils/toolbench/toolbench_data_utils.py
toolgrad/utils/toolbench/toolbench_langchain_utils.py
toolgrad/utils/toolbench/toolbench_utils.py
toolgrad-0.1.1.dist-info/licenses/LICENSE
toolgrad-0.1.1.dist-info/METADATA
toolgrad-0.1.1.dist-info/WHEEL
toolgrad-0.1.1.dist-info/top_level.txt
toolgrad-0.1.1.dist-info/RECORD
