Metadata-Version: 2.4
Name: toolgrad
Version: 0.1.1
Summary: Official Repo for ToolGrad: Efficient Tool-use Dataset Generation with Textual “Gradients”
Author: Zhongyi Zhou
License: CC-BY-4.0
Requires-Python: >=3.9
License-File: LICENSE
Requires-Dist: numpy>=1.26
Requires-Dist: langgraph>=0.2.19
Requires-Dist: langchain-core>=0.3.54
Requires-Dist: langchain>=0.3.18
Requires-Dist: langchain-openai>=0.3.3
Requires-Dist: pydantic>=2.9.1
Requires-Dist: langchain-community>0.3.17
Requires-Dist: pytz>=2025.1
Provides-Extra: dev
Requires-Dist: pytest>=6.0; extra == "dev"
Requires-Dist: yapf; extra == "dev"
Requires-Dist: isort; extra == "dev"
Requires-Dist: flake8; extra == "dev"
Dynamic: license-file
